{
  "db_name": "PostgreSQL",
  "query": "\n            update archives\n            set status = $2,\n                error = $3,\n                extracted_html = null,\n                extracted_title = null,\n                byline = null,\n                lang = null,\n                site_name = null,\n                published_time = null\n            where id = $1\n            returning id, bookmark_id, created_at, status as \"status: _\", error as \"error: Json<archive::Error>\", extracted_title, extracted_html, byline, lang, site_name, published_time as \"published_time: OffsetDateTime\"\n        ",
  "describe": {
    "columns": [
      {
        "ordinal": 0,
        "name": "id",
        "type_info": "Uuid"
      },
      {
        "ordinal": 1,
        "name": "bookmark_id",
        "type_info": "Uuid"
      },
      {
        "ordinal": 2,
        "name": "created_at",
        "type_info": "Timestamptz"
      },
      {
        "ordinal": 3,
        "name": "status: _",
        "type_info": {
          "Custom": {
            "name": "archive_status",
            "kind": {
              "Enum": [
                "Success",
                "Error",
                "Pending"
              ]
            }
          }
        }
      },
      {
        "ordinal": 4,
        "name": "error: Json<archive::Error>",
        "type_info": "Json"
      },
      {
        "ordinal": 5,
        "name": "extracted_title",
        "type_info": "Varchar"
      },
      {
        "ordinal": 6,
        "name": "extracted_html",
        "type_info": "Varchar"
      },
      {
        "ordinal": 7,
        "name": "byline",
        "type_info": "Varchar"
      },
      {
        "ordinal": 8,
        "name": "lang",
        "type_info": "Varchar"
      },
      {
        "ordinal": 9,
        "name": "site_name",
        "type_info": "Varchar"
      },
      {
        "ordinal": 10,
        "name": "published_time: OffsetDateTime",
        "type_info": "Timestamptz"
      }
    ],
    "parameters": {
      "Left": [
        "Uuid",
        {
          "Custom": {
            "name": "archive_status",
            "kind": {
              "Enum": [
                "Success",
                "Error",
                "Pending"
              ]
            }
          }
        },
        "Json"
      ]
    },
    "nullable": [
      false,
      false,
      false,
      false,
      true,
      true,
      true,
      true,
      true,
      true,
      true
    ]
  },
  "hash": "3aa9b9b3e244f96e2c21127af0da9c7ce76a5a7959c134fcc21132917f68b183"
}
